CHANGELOG.rst
LICENSE
MANIFEST.in
README.rst
requirements.txt
setup.cfg
setup.py
django3_grapesjs.egg-info/PKG-INFO
django3_grapesjs.egg-info/SOURCES.txt
django3_grapesjs.egg-info/dependency_links.txt
django3_grapesjs.egg-info/requires.txt
django3_grapesjs.egg-info/top_level.txt
django_grapesjs/__init__.py
django_grapesjs/settings.py
django_grapesjs/admin/__init__.py
django_grapesjs/admin/grepesjs_mixin.py
django_grapesjs/forms/__init__.py
django_grapesjs/forms/fields.py
django_grapesjs/forms/widgets.py
django_grapesjs/models/__init__.py
django_grapesjs/models/fields.py
django_grapesjs/static/css/grapes.min.css
django_grapesjs/static/css/grapesjs-plugin-filestack.css
django_grapesjs/static/css/grapesjs-preset-newsletter.css
django_grapesjs/static/css/grapesjs-preset-webpage.min.css
django_grapesjs/static/css/django_grapesjs/grapes.min.css
django_grapesjs/static/css/django_grapesjs/grapesjs-plugin-filestack.css
django_grapesjs/static/css/django_grapesjs/grapesjs-preset-newsletter.css
django_grapesjs/static/css/django_grapesjs/grapesjs-preset-webpage.min.css
django_grapesjs/static/fonts/FontAwesome.otf
django_grapesjs/static/fonts/fontawesome-webfont.eot
django_grapesjs/static/fonts/fontawesome-webfont.svg
django_grapesjs/static/fonts/fontawesome-webfont.ttf
django_grapesjs/static/fonts/fontawesome-webfont.woff
django_grapesjs/static/fonts/fontawesome-webfont.woff2
django_grapesjs/static/fonts/main-fonts.eot
django_grapesjs/static/fonts/main-fonts.svg
django_grapesjs/static/fonts/main-fonts.ttf
django_grapesjs/static/fonts/main-fonts.woff
django_grapesjs/static/js/grapes.js
django_grapesjs/static/js/grapes.min.js
django_grapesjs/static/js/grapes.min.js.map
django_grapesjs/static/js/grapesjs-custom-code.min.js
django_grapesjs/static/js/grapesjs-custom-code.min.js.map
django_grapesjs/static/js/grapesjs-plugin-ckeditor.min.js
django_grapesjs/static/js/grapesjs-plugin-filestack.min.js
django_grapesjs/static/js/grapesjs-preset-newsletter.min.js
django_grapesjs/static/js/grapesjs-preset-webpage.min.js
django_grapesjs/static/js/grapesjs-style-bg.min.js
django_grapesjs/static/js/grapesjs-style-bg.min.js.map
django_grapesjs/static/js/grapesjs-tui-image-editor.min.js
