Metadata-Version: 2.1
Name: django3-grapesjs
Version: 0.0.7
Summary: A small library for integrating the page builder "grapesjs" into django admin
Home-page: https://github.com/gulliverbms/django_grapesjs
Author: Mark Burkut
Author-email: josuedjh456@gmail.com
License: MIT
Keywords: page builder
Platform: UNKNOWN
Classifier: Framework :: Django :: 1.11
Classifier: Framework :: Django :: 2.0
Classifier: Natural Language :: English
Classifier: License :: OSI Approved :: MIT License
Classifier: Programming Language :: Python :: 3.5
Classifier: Programming Language :: Python :: 3.6
Classifier: Environment :: Web Environment
